openexchangerate.py
__pycache__/openexchangerate.cpython-36.opt-2.pyc
openexchangerate-1.5.5.dist-info/METADATA
openexchangerate-1.5.5.dist-info/RECORD
openexchangerate-1.5.5.dist-info/WHEEL
openexchangerate-1.5.5.dist-info/top_level.txt
openexchangerate-1.5.5.dist-info/zip-safe
